{
  "schema": "reproscore-repo-result/1.0",
  "repo": "biorack/omaat",
  "domain": "github.com",
  "clone_url": "https://github.com/biorack/omaat",
  "cloned_commit": "891da9558dc483abca8108b75b7e5e100c8773d1",
  "clone_timestamp_start_utc": "2026-05-11T10:19:25.642306+00:00",
  "clone_timestamp_end_utc": "2026-05-11T10:19:25.653394+00:00",
  "score_timestamp_start_utc": "2026-05-11T10:24:12.152977+00:00",
  "score_timestamp_end_utc": "2026-05-11T10:24:14.151422+00:00",
  "score_elapsed_seconds": 2.0,
  "ground_truth": {
    "source": "GigaScience execution database",
    "db_run_id": "20260511_101920",
    "giga_repo_id": 66,
    "giga_repo_commit": "e6fe8a71c46d42efeb3e99595c6bde4bae04796f",
    "article_published_date": "2023-01-24",
    "dominant_reason": "<Install Dependency Error>",
    "failure_mode": "install_dep",
    "total_exec_count": 2,
    "success_nb_count": 0,
    "nb_count": 4
  },
  "scores": {
    "rrs": 12.32,
    "penalty_E": 20,
    "penalty_A": 0.0,
    "penalty_seed": 0.0,
    "cat_E_raw": 5.0,
    "cat_E_gated": 0.53,
    "cat_A_raw": 22.0,
    "cat_A_gated": 4.71,
    "cat_D_raw": 50.22,
    "cat_D_gated": 10.04,
    "cat_C_raw": 61.11,
    "cat_C_gated": 9.17,
    "cat_S_raw": 78.67,
    "cat_S_gated": 7.87,
    "sub_dep_pinning": 20,
    "sub_container_spec": 0,
    "sub_env_bootstrap": 0,
    "sub_python_version_declared": 0,
    "sub_data_description": 20,
    "sub_data_pointer": 60,
    "sub_workflow_orchestration": 0,
    "sub_data_acquisition_script": 0,
    "sub_doc_structure": 25.0,
    "sub_install_instructions": 70,
    "sub_usage_examples": 60,
    "sub_docstring_coverage": 45.0,
    "sub_inline_explanation_density": 91.5,
    "sub_execution_entry_point": 0,
    "sub_reuse_metadata": 40,
    "sub_no_absolute_paths": 91.67,
    "sub_import_resolvability": 0.0,
    "sub_no_hardcoded_credentials": 100,
    "sub_silent_failure_masking": 94.44,
    "sub_seed_management": 100.0,
    "sub_notebook_exec_order": 83.33,
    "sub_test_file_presence": 100.0,
    "sub_expected_outputs": 0,
    "sub_ci_presence": 100,
    "sub_config_externalised": 0,
    "sub_hardware_requirements": 100
  }
}