{
  "schema": "reproscore-repo-result/1.0",
  "repo": "esa/NIDN",
  "domain": "github.com",
  "clone_url": "https://github.com/esa/NIDN",
  "cloned_commit": "a7416d3b8450a64a2855f4f13b6fc774485bef4f",
  "clone_timestamp_start_utc": "2026-05-11T10:19:25.913426+00:00",
  "clone_timestamp_end_utc": "2026-05-11T10:19:25.931322+00:00",
  "score_timestamp_start_utc": "2026-05-11T10:27:19.406483+00:00",
  "score_timestamp_end_utc": "2026-05-11T10:27:21.216953+00:00",
  "score_elapsed_seconds": 1.81,
  "ground_truth": {
    "source": "GigaScience execution database",
    "db_run_id": "20260511_101920",
    "giga_repo_id": 359,
    "giga_repo_commit": "4296ec94134526a55e91d1c8f1eb550fc71610fc",
    "article_published_date": "2022-12-22",
    "dominant_reason": "<Install Dependency Error>",
    "failure_mode": "install_dep",
    "total_exec_count": 8,
    "success_nb_count": 0,
    "nb_count": 14
  },
  "scores": {
    "rrs": 41.28,
    "penalty_E": 0.0,
    "penalty_A": 0.0,
    "penalty_seed": 10,
    "cat_E_raw": 55.0,
    "cat_E_gated": 16.5,
    "cat_A_raw": 18.0,
    "cat_A_gated": 3.49,
    "cat_D_raw": 65.71,
    "cat_D_gated": 13.14,
    "cat_C_raw": 86.0,
    "cat_C_gated": 12.9,
    "cat_S_raw": 52.51,
    "cat_S_gated": 5.25,
    "sub_dep_pinning": 60,
    "sub_container_spec": 0,
    "sub_env_bootstrap": 80,
    "sub_python_version_declared": 100,
    "sub_data_description": 0,
    "sub_data_pointer": 60,
    "sub_workflow_orchestration": 0,
    "sub_data_acquisition_script": 0,
    "sub_doc_structure": 75.0,
    "sub_install_instructions": 100,
    "sub_usage_examples": 60,
    "sub_docstring_coverage": 45.0,
    "sub_inline_explanation_density": 61.4,
    "sub_execution_entry_point": 0,
    "sub_reuse_metadata": 70,
    "sub_no_absolute_paths": 100,
    "sub_import_resolvability": 60.0,
    "sub_no_hardcoded_credentials": 100,
    "sub_silent_failure_masking": 100,
    "sub_seed_management": 0.0,
    "sub_notebook_exec_order": 78.57,
    "sub_test_file_presence": 100.0,
    "sub_expected_outputs": 40,
    "sub_ci_presence": 100,
    "sub_config_externalised": 0,
    "sub_hardware_requirements": 100
  }
}